{
  "Actor": {
    "types": ["capitalShip", "npc", "sublineCraft"],
    "templates": {
      "base": {
        "HP": {
          "value": 10,
          "min": 0,
          "max": 10
        },
        "description": ""
      }
    },
    "capitalShip": {
      "templates": ["base"],
      "attributes": {
        "points": {
          "value": 0
        },
        "defence": {
          "value": 0
        }
      },
      "traits&manouvers&tactics": {
        "traits": {
          "traitName" : "",
          "traitContent" : "",
          "traitAmount" : 1
        },
        "manouvers" : {
          "manouverName" : "",
          "manouverContent" : "",
          "manouverAmount" : 1
        },
        "tactics" : {
          "tacticName" : "",
          "tacticContent" : "",
          "tacticAmount" : 1
        }
      },
      "options": {
        "superheavy": {
          "value": 1
        },
        "primary": {
          "value": 1
        },
        "auxilliary": {
          "value": 1
        },
        "wings": {
          "value": 1
        },
        "escorts": {
          "value": 1
        }
      }
    },
    "npc": {
      "templates": ["base"],
      "traits&manouvers&tactics": {
        "traits": {
          "traitName" : "",
          "traitContent" : "",
          "traitAmount" : 1
        },
        "manouvers" : {
          "manouverName" : "",
          "manouverContent" : "",
          "manouverAmount" : 1
        },
        "tactics" : {
          "tacticName" : "",
          "tacticContent" : "",
          "tacticAmount" : 1
        },
        "weapons": ""
      }
    }
  },
  "Item": {
    "types": ["superheavy", "primary", "auxilliary", "sublineCraft", "system", "escortTemplate", "capitalHull", "npcClass", "tactic", "manouver"],
    "templates": {
      "base": {
        "Name": ""
      },
      "superheavy": {
        "templates": ["base"],
        "Damage": 1,
        "Range": "",
        "Charge": 0,
        "Reloading": 0,
        "Tags": "",
        "Effect": "",
        "Points": 0
      },
      "primary": {
        "templates": ["base"],
        "Damage": 1,
        "Range": "",
        "Charge": 0,
        "Reloading": 0,
        "Tags": "",
        "Effect": "",
        "Points": 0
      },
      "auxilliary": {
        "templates": ["base"],
        "Damage": 1,
        "Range": "",
        "Charge": 0,
        "Reloading": 0,
        "Tags": "",
        "Effect": "",
        "Points": 0
      },
      "sublineCraft": {
        "templates": ["base"],
        "Tactics": "",
        "Tags": "",
        "Effect": "",
        "Points": 0
      },
      "system": {
        "templates": ["base"],
        "Charge": 0,
        "Reloading": 0,
        "Tags": "",
        "Effect": "",
        "Tactics": "",
        "Manouvers": "",
        "Points": 0
      },
      "escortTemplate": {
        "templates": ["base"],
        "HP": "",
        "Tactics": "",
        "Tags": "",
        "Effect": "",
        "Manouvers": ""
      },
      "capitalHull": {
        "templates": ["base"],
        "HP": "",
        "Tactics": "",
        "Tags": "",
        "Effect": "",
        "Manouvers": ""
      }
    }
  }
}

